bit_cryptocompare/__init__.py
bit_cryptocompare/errors.py
bit_cryptocompare/parsers.py
bit_cryptocompare/config/__init__.py
bit_cryptocompare/tests/__init__.py
bit_cryptocompare/tests/test_util.py
bit_cryptocompare/util/__init__.py
bit_cryptocompare/util/data.py
bit_cryptocompare/util/url_factory.py
bit_cryptocompare/util/validate.py
bit_cryptocompare-0.0.1.dist-info/LICENSE
bit_cryptocompare-0.0.1.dist-info/METADATA
bit_cryptocompare-0.0.1.dist-info/WHEEL
bit_cryptocompare-0.0.1.dist-info/top_level.txt
bit_cryptocompare-0.0.1.dist-info/RECORD
