Metadata-Version: 2.1
Name: bit-cryptocompare
Version: 0.0.1
Summary: A Python wrapper for CryptoCompare package
Home-page: https://gitlab.com/frier17/bit_cryptocompare
Author: Aniefiok Friday
Author-email: frier17@a17s.co.uk
License: UNKNOWN
Platform: UNKNOWN
Classifier: Programming Language :: Python :: 3
Classifier: License :: OSI Approved :: MIT License
Classifier: Operating System :: OS Independent
Requires-Python: >=3.6
